{
    "repeat": "10", 
    "eid": "demo1", 
    "piid": "3", 
    "timeStamp": "1467256455", 
    "interval": "10", 
    "type": "web", 
    "data": [
        {
            "timeStamp": "1467256456.877", 
            "link": "http://www.google.com.hk/url?q=https://en.wikipedia.org/wiki/Microsoft_Network_Monitor", 
            "loadtime": "238"
        }, 
        {
            "timeStamp": "1467256467.853", 
            "link": "http://www.google.com.hk/url?q=https://zh.wikipedia.org/zh-hk/Wi-Fi", 
            "loadtime": "210"
        }, 
        {
            "timeStamp": "1467256478.874", 
            "link": "http://www.google.com.hk/url?q=https://zh.wikipedia.org/zh-hk/Wi-Fi", 
            "loadtime": "217"
        }, 
        {
            "timeStamp": "1467256489.895", 
            "link": "http://www.google.com.hk/url?q=https://www.raspberrypi.org/help/what-is-a-raspberry-pi/", 
            "loadtime": "217"
        }, 
        {
            "timeStamp": "1467256500.937", 
            "link": "http://www.google.com.hk/url?q=http://www.wi-fi.hk/en", 
            "loadtime": "224"
        }, 
        {
            "timeStamp": "1467256511.965", 
            "link": "http://www.google.com.hk/url?q=https://www.microsoft.com/en-us/download/details.aspx%3Fid%3D4865", 
            "loadtime": "215"
        }, 
        {
            "timeStamp": "1467256522.984", 
            "link": "http://www.google.com.hk/url?q=http://www.three.com.hk/website/appmanager/three/home%3F_nfpb%3Dtrue%26pageid%3D441001%26_pageLabel%3DP200470391219567710594", 
            "loadtime": "217"
        }, 
        {
            "timeStamp": "1467256533.978", 
            "link": "http://www.google.com.hk/url?q=http://hkcn.rs-online.com/web/generalDisplay.html%3Fid%3Draspberrypi", 
            "loadtime": "217"
        }, 
        {
            "timeStamp": "1467256544.986", 
            "link": "http://www.google.com.hk/url?q=https://zh.wikipedia.org/zh-hk/Wi-Fi", 
            "loadtime": "225"
        }, 
        {
            "timeStamp": "1467256555.978", 
            "link": "http://www.google.com.hk/url?q=https://www.microsoft.com/en-us/download/details.aspx%3Fid%3D4865", 
            "loadtime": "215"
        }
    ], 
    "location": "qr503"
}